{
  "name": "{{client_name}} - v11 Dashboard Live JSON",
  "nodes": [
    {
      "parameters": {
        "httpMethod": "GET",
        "path": "{{slug}}-v11",
        "responseMode": "responseNode",
        "options": {
          "responseHeaders": {
            "entries": [
              {
                "name": "Access-Control-Allow-Origin",
                "value": "*"
              },
              {
                "name": "Access-Control-Allow-Headers",
                "value": "Content-Type"
              }
            ]
          }
        }
      },
      "id": "webhook",
      "name": "Webhook",
      "type": "n8n-nodes-base.webhook",
      "typeVersion": 2,
      "position": [
        220,
        300
      ],
      "webhookId": "{{slug}}-v11"
    },
    {
      "parameters": {
        "jsCode": "const https = require('https');\nconst urlMod = require('url');\nfunction httpReq(method, rawUrl, headers, postBody) {\n  return new Promise((resolve, reject) => {\n    const parsed = urlMod.parse(rawUrl);\n    const opts = { hostname: parsed.hostname, path: parsed.path, method: method, headers: headers || {} };\n    const req = https.request(opts, (res) => {\n      let body = '';\n      res.on('data', c => body += c);\n      res.on('end', () => {\n        let json = null;\n        try { json = JSON.parse(body); } catch(e) {}\n        resolve({ ok: res.statusCode >= 200 && res.statusCode < 300, status: res.statusCode, json: json, text: body });\n      });\n    });\n    req.on('error', reject);\n    if (postBody) req.write(typeof postBody === 'string' ? postBody : JSON.stringify(postBody));\n    req.end();\n  });\n}\n\nconst SHEET_ID = '{{sheet_id}}';\nconst SHEET_URL = `https://docs.google.com/spreadsheets/d/${SHEET_ID}/gviz/tq?tqx=out:json&sheet=Raw_Jobs`;\n\ntry {\n  const resp = await fetch(SHEET_URL);\n  const text = resp.text;\n  // Strip Google's prefix/suffix\n  const jsonStr = text.replace(/^[^{]*/, '').replace(/[^}]*$/, '');\n  const data = JSON.parse(jsonStr);\n  const cols = data.table.cols.map(c => c.label);\n  const jobs = data.table.rows.map(row => {\n    const obj = {};\n    row.c.forEach((cell, i) => {\n      if (cols[i]) obj[cols[i]] = cell ? (cell.v || '') : '';\n    });\n    return obj;\n  });\n  return [{ json: { jobs, updated: new Date().toISOString(), source: 'google_sheets' } }];\n} catch(e) {\n  return [{ json: { jobs: [], error: e.message } }];\n}\n"
      },
      "id": "read-sheet",
      "name": "Read Sheet Data",
      "type": "n8n-nodes-base.code",
      "typeVersion": 2,
      "position": [
        440,
        300
      ]
    },
    {
      "parameters": {
        "respondWith": "json",
        "responseBody": "={{ $json }}",
        "options": {}
      },
      "id": "respond",
      "name": "Respond",
      "type": "n8n-nodes-base.respondToWebhook",
      "typeVersion": 1.1,
      "position": [
        660,
        300
      ]
    }
  ],
  "connections": {
    "Webhook": {
      "main": [
        [
          {
            "node": "Read Sheet Data",
            "type": "main",
            "index": 0
          }
        ]
      ]
    },
    "Read Sheet Data": {
      "main": [
        [
          {
            "node": "Respond",
            "type": "main",
            "index": 0
          }
        ]
      ]
    }
  },
  "settings": {
    "executionTimeout": 30
  }
}